LICENSE.txt
MANIFEST.in
README.rst
setup.py
django_hilbert.egg-info/PKG-INFO
django_hilbert.egg-info/SOURCES.txt
django_hilbert.egg-info/dependency_links.txt
django_hilbert.egg-info/not-zip-safe
django_hilbert.egg-info/top_level.txt
hilbert/__init__.py
hilbert/decorators.py
hilbert/finders.py
hilbert/http.py
hilbert/middleware.py
hilbert/models.py
hilbert/test.py
hilbert/views.py
hilbert/static/js/jquery.dj.hilbert.js
hilbert/tests/__init__.py
hilbert/tests/base.py
hilbert/tests/decorators.py
hilbert/tests/http.py
hilbert/tests/middleware.py
hilbert/tests/runtests.py
hilbert/tests/test.py
hilbert/tests/urls.py