Metadata-Version: 1.1
Name: django-hilbert
Version: 0.4.2
Summary: django-hilbert is one of many Django apps which is a loose collection of utility functions. It is a mixture of Python code and Javascript that I find myself writing over and  over. Primarily it focuses around utilities for AJAX and testing.
Home-page: https://github.com/mlavin/django-hilbert
Author: Mark Lavin
Author-email: markdlavin@gmail.com
License: LICENSE.txt
Platform: UNKNOWN
Classifier: Topic :: Internet :: WWW/HTTP :: Dynamic Content
Classifier: Intended Audience :: Developers
Classifier: License :: OSI Approved :: BSD License
Classifier: Programming Language :: Python
Classifier: Topic :: Software Development :: Libraries :: Python Modules
Classifier: Development Status :: 4 - Beta
Classifier: Operating System :: OS Independent
